{
  "youth_keywords": [
    "U7","U8","U9","U10","U11","U12","U13","U14","U15","U16","U17","U18",
    "Colts","Youth","Academy","Strikers","Juniors","Jnrs","Spartans","Falcons","Eagles","Tigers",
    "Jets","Panthers","Dragons","Cobras","Pumas","Wildcats","Leopards","Merlins","Knights","Warriors","Sharks",
    "Barrons","Rhinos","Broncos","Blues","Blazers","Rovers","Harriers","Centurions","Titans","Jaguars",
    "Tornadoes","Kingfishers","Ravens","Emeralds","Gems","Moonstone","Pearls","Ruby's","Sapphires","Tigresses",
    "Comets","Irons","Jags","Spiders","Robins","Storm","Kestrels","Pandas","Wolves","Y","Minors","Aces",
    "Avengers","Cannons","Invictus","Lions","Hearts","Ballers","Hornets","Arrows","Archers",
    "Diamonds","Rockets","Royals","Ambers","Hurricanes","Lightning","Lynxs","Halos","J","Junior",
    "Blades","Phantom","Predators","Sonics","Tiempo's","Vipers","Lasers","Phantoms","Wasps","Bees",
    "Tangerines","Stingers","Vespas","Sunday U13","Messi's","Neymar's","Ronaldo's","Iniesta's","Xavi's","Figo's","Maradona's","Cruyff's",
    "Pirates", "Gunners", "Hammers", "Pythons", "Dolphins", "YFC", "Magpies", "Bulldogs", "Scorpions", "Windmills", "Giants", "Raiders",
    "Vikings", "Vixens", "Whirwinds", "Kits", "Shields", "Swords", "Foxes", "Hawks", "Ospreys", "Roses", "Cheetahs", "Wild Horses", "Tawnys",
    "Phoenixes", "All Stars", "Devils", "Cubs", "Raptors", "Woodpeckers", "Boys", "Rosso", "Thundercats", "Rojas", "Mavericks",
    "Flames", "Knights"
  ],
  "mens_keywords": [
    "Seniors","1st","First","Mens","Reserves","Veterans","Vets","Development","Devs","res","Res",
    "A","B","C","D","Dev","Under 23","Senior","Conference","Premiership","Championship","Over",
    "3rds","2nds","4 ths","Thirds","Seconds","Sundays","Sun","Legends", "II", "Under 23s", "Masters", "Sunday"
  ],
  "ladies_keywords": ["Ladies","Girls","Belles","Lionesses","Women","Womens","ladies"],
  "color_keywords": [
    "Blue","Blues","Grey","White","Black","Orange","Red","Yellow","Green","UWhite","Cyans","Navy","Sky",
    "Purple","Pink","Turquoise","Magenta","Maroon","Teal","Lavender","Beige","Silver","Gold","Copper",
    "Crimson","Mint","Burgundy","Claret","Ambers","Blacks","Reds","Whites","Greens" , "Purples", "Yellows", "Tangerine"
  ],
  "disability_keywords": [
    "Disability","Inclusive","Inclusion","Special","Ability","Adaptive","Para","Paralympic","Amputee",
    "Blind","Visually","Hearing","Wheelchair","Football for All","Inclusive Football"
  ],
  "abbreviation_map": {
    "UTD": "United",
    "Ath": "Athletic",
    "ATH": "Athletic"
  },
  "club_suffixes": ["United","City","Town","Rovers","Athletic","FC"]
}
